hueclipse-3.0.0.dist-info/METADATA
hueclipse-3.0.0.dist-info/WHEEL
hueclipse/__init__.py
hueclipse/hueclipse.cp311-win_amd64.pyd
hueclipse-3.0.0.dist-info/RECORD
