Metadata-Version: 2.4
Name: hueclipse
Version: 3.0.0
Summary: Image Processing Library made in Rust
Keywords: hueclipse,image,rust,erase,color,transparent,rotate,flip,contrast,random
Home-Page: https://github.com/AdvikCh/Softwares.Hueclipse.git
Author: Advik Chaudhary <advik.ch@gmail.com>
Author-email: Advik Chaudhary <advik.ch@gmail.com>
License: MIT
Project-URL: Source Code, https://github.com/AdvikCh/Softwares.Hueclipse.git
